{
	"fileVersion": 1,
	"versions": {
		"automem": "0.6.11",
		"botan": "1.12.19",
		"botan-math": "1.0.3",
		"cachetools": "0.4.2",
		"dcd": "0.16.2",
		"dfmt": "0.15.2",
		"diet-complete": "0.0.3",
		"diet-ng": "1.8.4",
		"dscanner": "0.16.0-beta.5",
		"dub": "1.40.0",
		"during": "0.3.0",
		"emsi_containers": "0.9.0",
		"eventcore": "0.9.38",
		"fuzzymatch": "1.0.0",
		"inifiled": "1.3.3",
		"isfreedesktop": "0.1.1",
		"libasync": "0.8.6",
		"libddoc": "0.8.0",
		"libdparse": "0.25.1",
		"memutils": "1.0.10",
		"mir-algorithm": "3.22.4",
		"mir-core": "1.7.3",
		"mir-cpuid": "1.2.11",
		"mir-ion": "2.3.5",
		"mir-linux-kernel": "1.0.1",
		"msgpack-d": "1.0.5",
		"openssl": "3.4.0",
		"openssl-static": "1.0.5+3.0.8",
		"requests": "2.2.0",
		"rm-rf": "0.1.0",
		"sdlfmt": "0.1.1",
		"sdlite": "1.1.2",
		"silly": "1.1.1",
		"standardpaths": "0.8.2",
		"stdx-allocator": "2.77.5",
		"taggedalgebraic": "0.11.24",
		"test_allocator": "0.3.4",
		"unit-threaded": "2.2.3",
		"vibe-container": "1.7.1",
		"vibe-core": "2.13.3",
		"vibe-d": "0.10.3",
		"vibe-http": "1.3.2",
		"vibe-inet": "1.2.0",
		"vibe-serialization": "1.1.3",
		"vibe-stream": "1.3.0",
		"xdgpaths": "0.2.5"
	}
}
